google/cloud/bigquery_storage/__init__.py
google/cloud/bigquery_storage/gapic_version.py
google/cloud/bigquery_storage/py.typed
google/cloud/bigquery_storage_v1/__init__.py
google/cloud/bigquery_storage_v1/client.py
google/cloud/bigquery_storage_v1/exceptions.py
google/cloud/bigquery_storage_v1/gapic_metadata.json
google/cloud/bigquery_storage_v1/gapic_types.py
google/cloud/bigquery_storage_v1/gapic_version.py
google/cloud/bigquery_storage_v1/py.typed
google/cloud/bigquery_storage_v1/reader.py
google/cloud/bigquery_storage_v1/writer.py
google/cloud/bigquery_storage_v1/services/__init__.py
google/cloud/bigquery_storage_v1/services/big_query_read/__init__.py
google/cloud/bigquery_storage_v1/services/big_query_read/async_client.py
google/cloud/bigquery_storage_v1/services/big_query_read/client.py
google/cloud/bigquery_storage_v1/services/big_query_read/transports/__init__.py
google/cloud/bigquery_storage_v1/services/big_query_read/transports/base.py
google/cloud/bigquery_storage_v1/services/big_query_read/transports/grpc.py
google/cloud/bigquery_storage_v1/services/big_query_read/transports/grpc_asyncio.py
google/cloud/bigquery_storage_v1/services/big_query_write/__init__.py
google/cloud/bigquery_storage_v1/services/big_query_write/async_client.py
google/cloud/bigquery_storage_v1/services/big_query_write/client.py
google/cloud/bigquery_storage_v1/services/big_query_write/transports/__init__.py
google/cloud/bigquery_storage_v1/services/big_query_write/transports/base.py
google/cloud/bigquery_storage_v1/services/big_query_write/transports/grpc.py
google/cloud/bigquery_storage_v1/services/big_query_write/transports/grpc_asyncio.py
google/cloud/bigquery_storage_v1/types/__init__.py
google/cloud/bigquery_storage_v1/types/annotations.py
google/cloud/bigquery_storage_v1/types/arrow.py
google/cloud/bigquery_storage_v1/types/avro.py
google/cloud/bigquery_storage_v1/types/protobuf.py
google/cloud/bigquery_storage_v1/types/storage.py
google_cloud_bigquery_storage-2.33.0.dist-info/licenses/LICENSE
google_cloud_bigquery_storage-2.33.0.dist-info/METADATA
google_cloud_bigquery_storage-2.33.0.dist-info/WHEEL
google_cloud_bigquery_storage-2.33.0.dist-info/top_level.txt
google_cloud_bigquery_storage-2.33.0.dist-info/RECORD
